{
  "file": {
    "uploading": "Uploading file...",
    "upload": "Upload",
    "selectFile": "Select a Final Cut Pro .fcpxml file containing subtitles",
    "createFile": "Create file",
    "creatingFile": "Creating file...",
    "download": "Download",
    "cancel": "Cancel"
  },
  "translate": {
    "aiAssistant": "AI translation assistant",
    "translateSubtitles": "Translate subtitles",
    "language": "Language",
    "subtitle": "Subtitle",
    "warningLength": "red : translation is 10% longer than the original",
    "downloadExcelZip": "Export Excel files",
    "uploadTranslatedFile": "Import Translated file",
    "selectTranslationFile": "Select the Excel file with the translations",
    "createTranslatedFcpxml": "Create translated Final Cut Pro file"
  }
}
